README.md
setup.py
wscraper/__init__.py
wscraper/console.py
wscraper.egg-info/PKG-INFO
wscraper.egg-info/SOURCES.txt
wscraper.egg-info/dependency_links.txt
wscraper.egg-info/entry_points.txt
wscraper.egg-info/top_level.txt
wscraper/analysis/__init__.py
wscraper/analysis/article_iterator.py
wscraper/analysis/both_iterator.py
wscraper/analysis/combined_iterator.py
wscraper/analysis/entry_iterator.py
wscraper/analysis/page_iterator.py
wscraper/analysis/paragraph_iterator.py
wscraper/analysis/parser.py
wscraper/analysis/redirection_iterator.py
wscraper/base/__init__.py
wscraper/base/builder.py
wscraper/base/config.py
wscraper/base/constant.py
wscraper/base/wscraper_exception.py
wscraper/language/__init__.py
wscraper/language/english.py
wscraper/language/japanese.py
wscraper/language/language_base.py
wscraper/language/wscraper_language_error.py
wscraper/page/__init__.py
wscraper/page/entry.py
wscraper/page/redirection.py
wscraper/utility/__init__.py
wscraper/utility/file_manager.py
wscraper/utility/file_writer.py
wscraper/utility/progress_manager.py