Metadata-Version: 2.1
Name: wscraper
Version: 0.2.1
Summary: Scraping documents from a dump XML file of Wikipedia.
Home-page: https://github.com/tfull/wikipedia_scraper
Author: T.Furukawa
Author-email: tfurukawa.mail@gmail.com
License: MIT License
Keywords: Wikipedia
Platform: UNKNOWN
